[
  {
    "cell_type": "LNCaP clone FGC",
    "effect": 1.904139849941714,
    "abs_effect": 1.904139849941714,
    "best_track": "DNASE/EFO:0005726 DNase-seq/.",
    "n_tracks": 3
  },
  {
    "cell_type": "epithelial cell of proximal tubule",
    "effect": 1.6253728981756115,
    "abs_effect": 1.6253728981756115,
    "best_track": "DNASE/CL:0002306 DNase-seq/.",
    "n_tracks": 9
  },
  {
    "cell_type": "renal cortical epithelial cell",
    "effect": 1.4977183371703613,
    "abs_effect": 1.4977183371703613,
    "best_track": "DNASE/CL:0002584 DNase-seq/.",
    "n_tracks": 7
  }
]